{
    "n_rows": 42766,
    "n_columns": 73,
    "provenance": {
        "created by": {
            "name": "MetaSynth",
            "version": "0.2.2.dev4+g2c9370e",
            "privacy": null
        },
        "creation time": "2023-02-15T16:12:54.074586"
    },
    "vars": [
        {
            "name": "nr. sessions",
            "type": "continuous",
            "dtype": "Float64",
            "prop_missing": 0.0,
            "distribution": {
                "name": "TruncatedNormalDistribution",
                "parameters": {
                    "lower_bound": -1e-08,
                    "upper_bound": 2.00000001,
                    "mu": -103.98792451180151,
                    "sigma": 14.23941121904261
                }
            }
        },
        {
            "name": "total km",
            "type": "continuous",
            "dtype": "Float64",
            "prop_missing": 0.0,
            "distribution": {
                "name": "TruncatedNormalDistribution",
                "parameters": {
                    "lower_bound": -1e-08,
                    "upper_bound": 55.90000001,
                    "mu": -565.6880431574602,
                    "sigma": 63.93358150141152
                }
            }
        },
        {
            "name": "km Z3-4",
            "type": "continuous",
            "dtype": "Float64",
            "prop_missing": 0.0,
            "distribution": {
                "name": "TruncatedNormalDistribution",
                "parameters": {
                    "lower_bound": -1e-08,
                    "upper_bound": 42.200000010000004,
                    "mu": -859.7444342269379,
                    "sigma": 24.447257652365266
                }
            }
        },
        {
            "name": "km Z5-T1-T2",
            "type": "continuous",
            "dtype": "Float64",
            "prop_missing": 0.0,
            "distribution": {
                "name": "TruncatedNormalDistribution",
                "parameters": {
                    "lower_bound": -1e-08,
                    "upper_bound": 48.00000001,
                    "mu": -494.413476371155,
                    "sigma": 16.995317143163785
                }
            }
        },
        {
            "name": "km sprinting",
            "type": "continuous",
            "dtype": "Float64",
            "prop_missing": 0.0,
            "distribution": {
                "name": "TruncatedNormalDistribution",
                "parameters": {
                    "lower_bound": -1e-08,
                    "upper_bound": 40.00000001,
                    "mu": -191.8416936621342,
                    "sigma": 3.7526766164282
                }
            }
        },
        {
            "name": "strength training",
            "type": "continuous",
            "dtype": "Float64",
            "prop_missing": 0.0,
            "distribution": {
                "name": "TruncatedNormalDistribution",
                "parameters": {
                    "lower_bound": -1e-08,
                    "upper_bound": 2.00000001,
                    "mu": -207.81968600312055,
                    "sigma": 4.9314503584892755
                }
            }
        },
        {
            "name": "hours alternative",
            "type": "continuous",
            "dtype": "Float64",
            "prop_missing": 0.0,
            "distribution": {
                "name": "TruncatedNormalDistribution",
                "parameters": {
                    "lower_bound": -1e-08,
                    "upper_bound": 10.220000010000001,
                    "mu": -299.33731770481666,
                    "sigma": 7.0085636806039195
                }
            }
        },
        {
            "name": "perceived exertion",
            "type": "continuous",
            "dtype": "Float64",
            "prop_missing": 0.0,
            "distribution": {
                "name": "TruncatedNormalDistribution",
                "parameters": {
                    "lower_bound": -0.01000001,
                    "upper_bound": 1.00000001,
                    "mu": -97.24596171037675,
                    "sigma": 5.346165113426183
                }
            }
        },
        {
            "name": "perceived trainingSuccess",
            "type": "continuous",
            "dtype": "Float64",
            "prop_missing": 0.0,
            "distribution": {
                "name": "TruncatedNormalDistribution",
                "parameters": {
                    "lower_bound": -0.01000001,
                    "upper_bound": 1.00000001,
                    "mu": -197.07812625458513,
                    "sigma": 10.48184724981309
                }
            }
        },
        {
            "name": "perceived recovery",
            "type": "continuous",
            "dtype": "Float64",
            "prop_missing": 0.0,
            "distribution": {
                "name": "TruncatedNormalDistribution",
                "parameters": {
                    "lower_bound": -0.01000001,
                    "upper_bound": 1.00000001,
                    "mu": -9.64005062143404,
                    "sigma": 1.4650884575932182
                }
            }
        },
        {
            "name": "nr. sessions.1",
            "type": "continuous",
            "dtype": "Float64",
            "prop_missing": 0.0,
            "distribution": {
                "name": "TruncatedNormalDistribution",
                "parameters": {
                    "lower_bound": -1e-08,
                    "upper_bound": 2.00000001,
                    "mu": -73.99308953315628,
                    "sigma": 11.983237974843895
                }
            }
        },
        {
            "name": "total km.1",
            "type": "continuous",
            "dtype": "Float64",
            "prop_missing": 0.0,
            "distribution": {
                "name": "TruncatedNormalDistribution",
                "parameters": {
                    "lower_bound": -1e-08,
                    "upper_bound": 55.90000001,
                    "mu": -835.5862214100576,
                    "sigma": 77.3638823847564
                }
            }
        },
        {
            "name": "km Z3-4.1",
            "type": "continuous",
            "dtype": "Float64",
            "prop_missing": 0.0,
            "distribution": {
                "name": "TruncatedNormalDistribution",
                "parameters": {
                    "lower_bound": -1e-08,
                    "upper_bound": 42.200000010000004,
                    "mu": -739.0185324524164,
                    "sigma": 22.721424062936112
                }
            }
        },
        {
            "name": "km Z5-T1-T2.1",
            "type": "continuous",
            "dtype": "Float64",
            "prop_missing": 0.0,
            "distribution": {
                "name": "TruncatedNormalDistribution",
                "parameters": {
                    "lower_bound": -1e-08,
                    "upper_bound": 48.00000001,
                    "mu": -871.452064424921,
                    "sigma": 22.433044421969043
                }
            }
        },
        {
            "name": "km sprinting.1",
            "type": "continuous",
            "dtype": "Float64",
            "prop_missing": 0.0,
            "distribution": {
                "name": "TruncatedNormalDistribution",
                "parameters": {
                    "lower_bound": -1e-08,
                    "upper_bound": 40.00000001,
                    "mu": -186.00232372426146,
                    "sigma": 3.691176987039116
                }
            }
        },
        {
            "name": "strength training.1",
            "type": "continuous",
            "dtype": "Float64",
            "prop_missing": 0.0,
            "distribution": {
                "name": "TruncatedNormalDistribution",
                "parameters": {
                    "lower_bound": -1e-08,
                    "upper_bound": 2.00000001,
                    "mu": -263.7311620681694,
                    "sigma": 5.577519296473352
                }
            }
        },
        {
            "name": "hours alternative.1",
            "type": "continuous",
            "dtype": "Float64",
            "prop_missing": 0.0,
            "distribution": {
                "name": "TruncatedNormalDistribution",
                "parameters": {
                    "lower_bound": -1e-08,
                    "upper_bound": 10.220000010000001,
                    "mu": -334.9153768075535,
                    "sigma": 7.431553326903193
                }
            }
        },
        {
            "name": "perceived exertion.1",
            "type": "continuous",
            "dtype": "Float64",
            "prop_missing": 0.0,
            "distribution": {
                "name": "TruncatedNormalDistribution",
                "parameters": {
                    "lower_bound": -0.01000001,
                    "upper_bound": 1.00000001,
                    "mu": -112.49367574413424,
                    "sigma": 5.70883294825608
                }
            }
        },
        {
            "name": "perceived trainingSuccess.1",
            "type": "continuous",
            "dtype": "Float64",
            "prop_missing": 0.0,
            "distribution": {
                "name": "TruncatedNormalDistribution",
                "parameters": {
                    "lower_bound": -0.01000001,
                    "upper_bound": 1.00000001,
                    "mu": -139.36471276057765,
                    "sigma": 8.834043148728657
                }
            }
        },
        {
            "name": "perceived recovery.1",
            "type": "continuous",
            "dtype": "Float64",
            "prop_missing": 0.0,
            "distribution": {
                "name": "TruncatedNormalDistribution",
                "parameters": {
                    "lower_bound": -0.01000001,
                    "upper_bound": 1.00000001,
                    "mu": -9.780338660895277,
                    "sigma": 1.4747768010884381
                }
            }
        },
        {
            "name": "nr. sessions.2",
            "type": "continuous",
            "dtype": "Float64",
            "prop_missing": 0.0,
            "distribution": {
                "name": "TruncatedNormalDistribution",
                "parameters": {
                    "lower_bound": -1e-08,
                    "upper_bound": 2.00000001,
                    "mu": -123.72694099032356,
                    "sigma": 15.47677291460946
                }
            }
        },
        {
            "name": "total km.2",
            "type": "continuous",
            "dtype": "Float64",
            "prop_missing": 0.0,
            "distribution": {
                "name": "TruncatedNormalDistribution",
                "parameters": {
                    "lower_bound": -1e-08,
                    "upper_bound": 55.90000001,
                    "mu": -783.3282996361421,
                    "sigma": 75.2018986839739
                }
            }
        },
        {
            "name": "km Z3-4.2",
            "type": "continuous",
            "dtype": "Float64",
            "prop_missing": 0.0,
            "distribution": {
                "name": "TruncatedNormalDistribution",
                "parameters": {
                    "lower_bound": -1e-08,
                    "upper_bound": 42.200000010000004,
                    "mu": -826.7384045973489,
                    "sigma": 23.957536817586824
                }
            }
        },
        {
            "name": "km Z5-T1-T2.2",
            "type": "continuous",
            "dtype": "Float64",
            "prop_missing": 0.0,
            "distribution": {
                "name": "TruncatedNormalDistribution",
                "parameters": {
                    "lower_bound": -1e-08,
                    "upper_bound": 48.00000001,
                    "mu": -907.8426216122471,
                    "sigma": 22.962267636653355
                }
            }
        },
        {
            "name": "km sprinting.2",
            "type": "continuous",
            "dtype": "Float64",
            "prop_missing": 0.0,
            "distribution": {
                "name": "TruncatedNormalDistribution",
                "parameters": {
                    "lower_bound": -1e-08,
                    "upper_bound": 40.00000001,
                    "mu": -184.32029220974914,
                    "sigma": 3.690504764396003
                }
            }
        },
        {
            "name": "strength training.2",
            "type": "continuous",
            "dtype": "Float64",
            "prop_missing": 0.0,
            "distribution": {
                "name": "TruncatedNormalDistribution",
                "parameters": {
                    "lower_bound": -1e-08,
                    "upper_bound": 2.00000001,
                    "mu": -207.94943831914424,
                    "sigma": 4.930035769993963
                }
            }
        },
        {
            "name": "hours alternative.2",
            "type": "continuous",
            "dtype": "Float64",
            "prop_missing": 0.0,
            "distribution": {
                "name": "TruncatedNormalDistribution",
                "parameters": {
                    "lower_bound": -1e-08,
                    "upper_bound": 10.220000010000001,
                    "mu": -255.65138713557906,
                    "sigma": 6.477512250713059
                }
            }
        },
        {
            "name": "perceived exertion.2",
            "type": "continuous",
            "dtype": "Float64",
            "prop_missing": 0.0,
            "distribution": {
                "name": "TruncatedNormalDistribution",
                "parameters": {
                    "lower_bound": -0.01000001,
                    "upper_bound": 1.00000001,
                    "mu": -79.92609177357394,
                    "sigma": 4.823406115891698
                }
            }
        },
        {
            "name": "perceived trainingSuccess.2",
            "type": "continuous",
            "dtype": "Float64",
            "prop_missing": 0.0,
            "distribution": {
                "name": "TruncatedNormalDistribution",
                "parameters": {
                    "lower_bound": -0.01000001,
                    "upper_bound": 1.00000001,
                    "mu": -220.2501512801712,
                    "sigma": 11.074871390262814
                }
            }
        },
        {
            "name": "perceived recovery.2",
            "type": "continuous",
            "dtype": "Float64",
            "prop_missing": 0.0,
            "distribution": {
                "name": "TruncatedNormalDistribution",
                "parameters": {
                    "lower_bound": -0.01000001,
                    "upper_bound": 1.00000001,
                    "mu": -9.636606547194924,
                    "sigma": 1.4657947396314093
                }
            }
        },
        {
            "name": "nr. sessions.3",
            "type": "continuous",
            "dtype": "Float64",
            "prop_missing": 0.0,
            "distribution": {
                "name": "TruncatedNormalDistribution",
                "parameters": {
                    "lower_bound": -1e-08,
                    "upper_bound": 2.00000001,
                    "mu": -74.44184201910228,
                    "sigma": 12.017835479661219
                }
            }
        },
        {
            "name": "total km.3",
            "type": "continuous",
            "dtype": "Float64",
            "prop_missing": 0.0,
            "distribution": {
                "name": "TruncatedNormalDistribution",
                "parameters": {
                    "lower_bound": -1e-08,
                    "upper_bound": 57.00000001,
                    "mu": -922.0245969829543,
                    "sigma": 81.26968680274898
                }
            }
        },
        {
            "name": "km Z3-4.3",
            "type": "continuous",
            "dtype": "Float64",
            "prop_missing": 0.0,
            "distribution": {
                "name": "TruncatedNormalDistribution",
                "parameters": {
                    "lower_bound": -1e-08,
                    "upper_bound": 42.200000010000004,
                    "mu": -893.7154046178158,
                    "sigma": 24.948542678063617
                }
            }
        },
        {
            "name": "km Z5-T1-T2.3",
            "type": "continuous",
            "dtype": "Float64",
            "prop_missing": 0.0,
            "distribution": {
                "name": "TruncatedNormalDistribution",
                "parameters": {
                    "lower_bound": -1e-08,
                    "upper_bound": 48.00000001,
                    "mu": -704.649382510186,
                    "sigma": 20.277413915580258
                }
            }
        },
        {
            "name": "km sprinting.3",
            "type": "continuous",
            "dtype": "Float64",
            "prop_missing": 0.0,
            "distribution": {
                "name": "TruncatedNormalDistribution",
                "parameters": {
                    "lower_bound": -1e-08,
                    "upper_bound": 40.00000001,
                    "mu": -228.34132419433243,
                    "sigma": 4.089319301344676
                }
            }
        },
        {
            "name": "strength training.3",
            "type": "continuous",
            "dtype": "Float64",
            "prop_missing": 0.0,
            "distribution": {
                "name": "TruncatedNormalDistribution",
                "parameters": {
                    "lower_bound": -1e-08,
                    "upper_bound": 2.00000001,
                    "mu": -248.24511322646896,
                    "sigma": 5.394074161544216
                }
            }
        },
        {
            "name": "hours alternative.3",
            "type": "continuous",
            "dtype": "Float64",
            "prop_missing": 0.0,
            "distribution": {
                "name": "TruncatedNormalDistribution",
                "parameters": {
                    "lower_bound": -1e-08,
                    "upper_bound": 10.220000010000001,
                    "mu": -208.78075634888097,
                    "sigma": 5.849923938267872
                }
            }
        },
        {
            "name": "perceived exertion.3",
            "type": "continuous",
            "dtype": "Float64",
            "prop_missing": 0.0,
            "distribution": {
                "name": "TruncatedNormalDistribution",
                "parameters": {
                    "lower_bound": -0.01000001,
                    "upper_bound": 1.00000001,
                    "mu": -78.2592938578674,
                    "sigma": 4.772214633933118
                }
            }
        },
        {
            "name": "perceived trainingSuccess.3",
            "type": "continuous",
            "dtype": "Float64",
            "prop_missing": 0.0,
            "distribution": {
                "name": "TruncatedNormalDistribution",
                "parameters": {
                    "lower_bound": -0.01000001,
                    "upper_bound": 1.00000001,
                    "mu": -352.5688913417678,
                    "sigma": 14.04589229523837
                }
            }
        },
        {
            "name": "perceived recovery.3",
            "type": "continuous",
            "dtype": "Float64",
            "prop_missing": 0.0,
            "distribution": {
                "name": "TruncatedNormalDistribution",
                "parameters": {
                    "lower_bound": -0.01000001,
                    "upper_bound": 1.00000001,
                    "mu": -10.555839078711172,
                    "sigma": 1.532018939469374
                }
            }
        },
        {
            "name": "nr. sessions.4",
            "type": "continuous",
            "dtype": "Float64",
            "prop_missing": 0.0,
            "distribution": {
                "name": "TruncatedNormalDistribution",
                "parameters": {
                    "lower_bound": -1e-08,
                    "upper_bound": 2.00000001,
                    "mu": -89.7469815180278,
                    "sigma": 13.216137865026962
                }
            }
        },
        {
            "name": "total km.4",
            "type": "continuous",
            "dtype": "Float64",
            "prop_missing": 0.0,
            "distribution": {
                "name": "TruncatedNormalDistribution",
                "parameters": {
                    "lower_bound": -1e-08,
                    "upper_bound": 55.90000001,
                    "mu": -529.826701213649,
                    "sigma": 61.91999842382597
                }
            }
        },
        {
            "name": "km Z3-4.4",
            "type": "continuous",
            "dtype": "Float64",
            "prop_missing": 0.0,
            "distribution": {
                "name": "TruncatedNormalDistribution",
                "parameters": {
                    "lower_bound": -1e-08,
                    "upper_bound": 42.200000010000004,
                    "mu": -726.2038681470774,
                    "sigma": 22.604850824271324
                }
            }
        },
        {
            "name": "km Z5-T1-T2.4",
            "type": "continuous",
            "dtype": "Float64",
            "prop_missing": 0.0,
            "distribution": {
                "name": "TruncatedNormalDistribution",
                "parameters": {
                    "lower_bound": -1e-08,
                    "upper_bound": 48.00000001,
                    "mu": -1113.3490201021334,
                    "sigma": 25.409822868799733
                }
            }
        },
        {
            "name": "km sprinting.4",
            "type": "continuous",
            "dtype": "Float64",
            "prop_missing": 0.0,
            "distribution": {
                "name": "TruncatedNormalDistribution",
                "parameters": {
                    "lower_bound": -1e-08,
                    "upper_bound": 40.00000001,
                    "mu": -250.3634508604721,
                    "sigma": 4.289422645445214
                }
            }
        },
        {
            "name": "strength training.4",
            "type": "continuous",
            "dtype": "Float64",
            "prop_missing": 0.0,
            "distribution": {
                "name": "TruncatedNormalDistribution",
                "parameters": {
                    "lower_bound": -1e-08,
                    "upper_bound": 2.00000001,
                    "mu": -132.54723312716376,
                    "sigma": 3.934046652863308
                }
            }
        },
        {
            "name": "hours alternative.4",
            "type": "continuous",
            "dtype": "Float64",
            "prop_missing": 0.0,
            "distribution": {
                "name": "TruncatedNormalDistribution",
                "parameters": {
                    "lower_bound": -1e-08,
                    "upper_bound": 10.00000001,
                    "mu": -168.87465181183615,
                    "sigma": 5.273757876529559
                }
            }
        },
        {
            "name": "perceived exertion.4",
            "type": "continuous",
            "dtype": "Float64",
            "prop_missing": 0.0,
            "distribution": {
                "name": "TruncatedNormalDistribution",
                "parameters": {
                    "lower_bound": -0.01000001,
                    "upper_bound": 1.00000001,
                    "mu": -101.49386560639378,
                    "sigma": 5.433654785940921
                }
            }
        },
        {
            "name": "perceived trainingSuccess.4",
            "type": "continuous",
            "dtype": "Float64",
            "prop_missing": 0.0,
            "distribution": {
                "name": "TruncatedNormalDistribution",
                "parameters": {
                    "lower_bound": -0.01000001,
                    "upper_bound": 1.00000001,
                    "mu": -146.90072214540814,
                    "sigma": 9.052571890636475
                }
            }
        },
        {
            "name": "perceived recovery.4",
            "type": "continuous",
            "dtype": "Float64",
            "prop_missing": 0.0,
            "distribution": {
                "name": "TruncatedNormalDistribution",
                "parameters": {
                    "lower_bound": -0.01000001,
                    "upper_bound": 1.00000001,
                    "mu": -9.223337504786478,
                    "sigma": 1.4356234140437882
                }
            }
        },
        {
            "name": "nr. sessions.5",
            "type": "continuous",
            "dtype": "Float64",
            "prop_missing": 0.0,
            "distribution": {
                "name": "TruncatedNormalDistribution",
                "parameters": {
                    "lower_bound": -1e-08,
                    "upper_bound": 2.00000001,
                    "mu": -88.6739446441821,
                    "sigma": 13.142419020456941
                }
            }
        },
        {
            "name": "total km.5",
            "type": "continuous",
            "dtype": "Float64",
            "prop_missing": 0.0,
            "distribution": {
                "name": "TruncatedNormalDistribution",
                "parameters": {
                    "lower_bound": -1e-08,
                    "upper_bound": 55.90000001,
                    "mu": -838.0366247153521,
                    "sigma": 77.89071222802487
                }
            }
        },
        {
            "name": "km Z3-4.5",
            "type": "continuous",
            "dtype": "Float64",
            "prop_missing": 0.0,
            "distribution": {
                "name": "TruncatedNormalDistribution",
                "parameters": {
                    "lower_bound": -1e-08,
                    "upper_bound": 42.200000010000004,
                    "mu": -602.8298211831661,
                    "sigma": 20.658728456075252
                }
            }
        },
        {
            "name": "km Z5-T1-T2.5",
            "type": "continuous",
            "dtype": "Float64",
            "prop_missing": 0.0,
            "distribution": {
                "name": "TruncatedNormalDistribution",
                "parameters": {
                    "lower_bound": -1e-08,
                    "upper_bound": 48.00000001,
                    "mu": -1000.9220526320398,
                    "sigma": 24.141051819019324
                }
            }
        },
        {
            "name": "km sprinting.5",
            "type": "continuous",
            "dtype": "Float64",
            "prop_missing": 0.0,
            "distribution": {
                "name": "TruncatedNormalDistribution",
                "parameters": {
                    "lower_bound": -1e-08,
                    "upper_bound": 40.00000001,
                    "mu": -198.69577012606337,
                    "sigma": 3.8060186326829015
                }
            }
        },
        {
            "name": "strength training.5",
            "type": "continuous",
            "dtype": "Float64",
            "prop_missing": 0.0,
            "distribution": {
                "name": "TruncatedNormalDistribution",
                "parameters": {
                    "lower_bound": -1e-08,
                    "upper_bound": 2.00000001,
                    "mu": -265.7502287958848,
                    "sigma": 5.562905986528177
                }
            }
        },
        {
            "name": "hours alternative.5",
            "type": "continuous",
            "dtype": "Float64",
            "prop_missing": 0.0,
            "distribution": {
                "name": "TruncatedNormalDistribution",
                "parameters": {
                    "lower_bound": -1e-08,
                    "upper_bound": 10.00000001,
                    "mu": -314.0431612170589,
                    "sigma": 7.158895520389233
                }
            }
        },
        {
            "name": "perceived exertion.5",
            "type": "continuous",
            "dtype": "Float64",
            "prop_missing": 0.0,
            "distribution": {
                "name": "TruncatedNormalDistribution",
                "parameters": {
                    "lower_bound": -0.01000001,
                    "upper_bound": 1.00000001,
                    "mu": -93.5766280177946,
                    "sigma": 5.218753367622721
                }
            }
        },
        {
            "name": "perceived trainingSuccess.5",
            "type": "continuous",
            "dtype": "Float64",
            "prop_missing": 0.0,
            "distribution": {
                "name": "TruncatedNormalDistribution",
                "parameters": {
                    "lower_bound": -0.01000001,
                    "upper_bound": 1.00000001,
                    "mu": -167.31834725642878,
                    "sigma": 9.655776006986121
                }
            }
        },
        {
            "name": "perceived recovery.5",
            "type": "continuous",
            "dtype": "Float64",
            "prop_missing": 0.0,
            "distribution": {
                "name": "TruncatedNormalDistribution",
                "parameters": {
                    "lower_bound": -0.01000001,
                    "upper_bound": 1.00000001,
                    "mu": -9.95276377062806,
                    "sigma": 1.4895788532956504
                }
            }
        },
        {
            "name": "nr. sessions.6",
            "type": "continuous",
            "dtype": "Float64",
            "prop_missing": 0.0,
            "distribution": {
                "name": "TruncatedNormalDistribution",
                "parameters": {
                    "lower_bound": -1e-08,
                    "upper_bound": 2.00000001,
                    "mu": -83.41477266435125,
                    "sigma": 12.713298600542473
                }
            }
        },
        {
            "name": "total km.6",
            "type": "continuous",
            "dtype": "Float64",
            "prop_missing": 0.0,
            "distribution": {
                "name": "TruncatedNormalDistribution",
                "parameters": {
                    "lower_bound": -1e-08,
                    "upper_bound": 55.90000001,
                    "mu": -602.4710341898826,
                    "sigma": 66.03383644558252
                }
            }
        },
        {
            "name": "km Z3-4.6",
            "type": "continuous",
            "dtype": "Float64",
            "prop_missing": 0.0,
            "distribution": {
                "name": "TruncatedNormalDistribution",
                "parameters": {
                    "lower_bound": -1e-08,
                    "upper_bound": 42.200000010000004,
                    "mu": -743.8504663508796,
                    "sigma": 23.039687668599235
                }
            }
        },
        {
            "name": "km Z5-T1-T2.6",
            "type": "continuous",
            "dtype": "Float64",
            "prop_missing": 0.0,
            "distribution": {
                "name": "TruncatedNormalDistribution",
                "parameters": {
                    "lower_bound": -1e-08,
                    "upper_bound": 48.00000001,
                    "mu": -604.9347734612752,
                    "sigma": 18.766029199788708
                }
            }
        },
        {
            "name": "km sprinting.6",
            "type": "continuous",
            "dtype": "Float64",
            "prop_missing": 0.0,
            "distribution": {
                "name": "TruncatedNormalDistribution",
                "parameters": {
                    "lower_bound": -1e-08,
                    "upper_bound": 40.00000001,
                    "mu": -188.1516991294041,
                    "sigma": 3.7059956276655583
                }
            }
        },
        {
            "name": "strength training.6",
            "type": "continuous",
            "dtype": "Float64",
            "prop_missing": 0.0,
            "distribution": {
                "name": "TruncatedNormalDistribution",
                "parameters": {
                    "lower_bound": -1e-08,
                    "upper_bound": 2.00000001,
                    "mu": -157.59015129577384,
                    "sigma": 4.286284637954743
                }
            }
        },
        {
            "name": "hours alternative.6",
            "type": "continuous",
            "dtype": "Float64",
            "prop_missing": 0.0,
            "distribution": {
                "name": "TruncatedNormalDistribution",
                "parameters": {
                    "lower_bound": -1e-08,
                    "upper_bound": 20.00000001,
                    "mu": -300.8482445953387,
                    "sigma": 6.976547574105408
                }
            }
        },
        {
            "name": "perceived exertion.6",
            "type": "continuous",
            "dtype": "Float64",
            "prop_missing": 0.0,
            "distribution": {
                "name": "TruncatedNormalDistribution",
                "parameters": {
                    "lower_bound": -0.01000001,
                    "upper_bound": 1.00000001,
                    "mu": -101.6472001839793,
                    "sigma": 5.434835086800781
                }
            }
        },
        {
            "name": "perceived trainingSuccess.6",
            "type": "continuous",
            "dtype": "Float64",
            "prop_missing": 0.0,
            "distribution": {
                "name": "TruncatedNormalDistribution",
                "parameters": {
                    "lower_bound": -0.01000001,
                    "upper_bound": 1.00000001,
                    "mu": -148.53554384067624,
                    "sigma": 9.050581184624413
                }
            }
        },
        {
            "name": "perceived recovery.6",
            "type": "continuous",
            "dtype": "Float64",
            "prop_missing": 0.0,
            "distribution": {
                "name": "TruncatedNormalDistribution",
                "parameters": {
                    "lower_bound": -0.01000001,
                    "upper_bound": 1.00000001,
                    "mu": -9.694373461552319,
                    "sigma": 1.4704986205526034
                }
            }
        },
        {
            "name": "Athlete ID",
            "type": "discrete",
            "dtype": "Int64",
            "prop_missing": 0.0,
            "distribution": {
                "name": "DiscreteUniformDistribution",
                "parameters": {
                    "low": 0,
                    "high": 74
                }
            }
        },
        {
            "name": "injury",
            "type": "discrete",
            "dtype": "Int64",
            "prop_missing": 0.0,
            "distribution": {
                "name": "PoissonDistribution",
                "parameters": {
                    "mu": 0.013632324743955478
                }
            }
        },
        {
            "name": "Date",
            "type": "discrete",
            "dtype": "Int64",
            "prop_missing": 0.0,
            "distribution": {
                "name": "DiscreteUniformDistribution",
                "parameters": {
                    "low": 0,
                    "high": 2674
                }
            }
        }
    ]
}